cronberry/__init__.py
cronberry/app.py
cronberry/fields.py
cronberry/py.typed
cronberry-5.0.0.post0.dist-info/LICENSE
cronberry-5.0.0.post0.dist-info/METADATA
cronberry-5.0.0.post0.dist-info/WHEEL
cronberry-5.0.0.post0.dist-info/entry_points.txt
cronberry-5.0.0.post0.dist-info/top_level.txt
cronberry-5.0.0.post0.dist-info/RECORD
