Metadata-Version: 2.2
Name: cronberry
Version: 5.0.0.post0
Summary: Library and CLI for working with multiple cron jobs within a single cron table
Author-email: Alec Delaney <tekktrik@gmail.com>
License: GPL-3.0-or-later
Project-URL: Homepage, https://github.com/tekktrik/cronberry
Project-URL: Repository, https://github.com/tekktrik/cronberry
Project-URL: Documentation, https://cronberry.readthedocs.io/en/latest/
Keywords: cron,crontab,tools,scheduler
Classifier: Programming Language :: Python :: 3
Classifier: Programming Language :: Python :: 3.10
Classifier: Programming Language :: Python :: 3.11
Classifier: Programming Language :: Python :: 3.12
Classifier: Programming Language :: Python :: 3.13
Classifier: Natural Language :: English
Classifier: Operating System :: POSIX :: Linux
Classifier: Intended Audience :: Developers
Classifier: Development Status :: 5 - Production/Stable
Classifier: License :: OSI Approved :: GNU General Public License v3 or later (GPLv3+)
Classifier: Environment :: Console
Classifier: Topic :: Software Development :: Libraries
Classifier: Topic :: Utilities
Classifier: Typing :: Typed
Requires-Python: >=3.10
License-File: LICENSE
Requires-Dist: click~=8.1
Provides-Extra: dev
Requires-Dist: pre-commit~=4.1; extra == "dev"
Requires-Dist: pytest~=8.3; extra == "dev"
Requires-Dist: coverage~=7.6; extra == "dev"
